passbit/__init__.py
passbit/__main__.py
passbit/app.py
passbit/create_db.py
passbit/create_entry.py
passbit/import_export_db.py
passbit/key_file_generator.py
passbit/language.py
passbit/modify_database.py
passbit/modify_entry.py
passbit/open_db.py
passbit/password_generator.py
passbit/pb_crypto.py
passbit/settings.py
passbit/settings_editor.py
passbit/show_db_info.py
passbit/show_info.py
passbit/words/__init__.py
passbit/words/english_words_10k.txt
passbit/words/russian_words_10k.txt
PassBit-0.1.4.dist-info/LICENSE
PassBit-0.1.4.dist-info/METADATA
PassBit-0.1.4.dist-info/WHEEL
PassBit-0.1.4.dist-info/top_level.txt
PassBit-0.1.4.dist-info/RECORD
