Metadata-Version: 2.1
Name: PassBit
Version: 0.1.4
Summary: Open-source cross-platform encrypted password manager
Author: Kolbanidze
License: GNU GENERAL PUBLIC LICENSE
Project-URL: Homepage, https://github.com/kolbanidze/passbit
Keywords: Password manager,Encrypted storage,Encrypted passwords,AES,Argon2ID,Password,Password storage
Classifier: Development Status :: 4 - Beta
Classifier: License :: OSI Approved :: GNU General Public License v3 (GPLv3)
Classifier: Natural Language :: Russian
Classifier: Natural Language :: English
Classifier: Operating System :: OS Independent
Classifier: Programming Language :: Python
Requires-Python: >=3.6
License-File: LICENSE
Requires-Dist: argon2-cffi
Requires-Dist: CTkMessagebox
Requires-Dist: customtkinter
Requires-Dist: pycryptodome
Requires-Dist: pyotp
Requires-Dist: pyperclip
Requires-Dist: Requests
